dpai/__init__.py
dpai/__main__.py
dpai/fastapi_main.py
dpai/main.py
dpai/model_manager.py
dpai/utils.py
dpai/configs/logging_config.ini
dpai/model_db/crud.py
dpai/model_db/db_setup.py
dpai/model_db/models.py
dpai/model_db/__pycache__/crud.cpython-311.pyc
dpai/model_db/__pycache__/db_setup.cpython-311.pyc
dpai/model_db/__pycache__/models.cpython-311.pyc
dpai-0.1.0.dist-info/LICENSE
dpai-0.1.0.dist-info/METADATA
dpai-0.1.0.dist-info/WHEEL
dpai-0.1.0.dist-info/entry_points.txt
dpai-0.1.0.dist-info/top_level.txt
dpai-0.1.0.dist-info/RECORD
