Metadata-Version: 2.1
Name: dpai
Version: 0.1.0
Summary: ML Model Serving Package
Author-email: "Zhenlin Wang (Criss)" <zhenlinw@cs.cmu.edu>
License: Apache License
Project-URL: Documentation, https://dpai.readthedocs.io
Project-URL: Homepage, https://github.com/criss-wang/dpai
Classifier: Development Status :: 4 - Beta
Classifier: Programming Language :: Python :: 3.8
Classifier: Programming Language :: Python :: 3.9
Classifier: Programming Language :: Python :: 3.10
Classifier: Programming Language :: Python :: 3.11
Classifier: Intended Audience :: Developers
Classifier: Operating System :: MacOS
Classifier: Operating System :: POSIX :: Linux
Classifier: Operating System :: Microsoft :: Windows
Classifier: License :: OSI Approved :: Apache Software License
Classifier: Topic :: Scientific/Engineering :: Artificial Intelligence
Classifier: Topic :: Software Development :: Libraries
Requires-Python: >=3.8
License-File: LICENSE
Requires-Dist: objprint >0.1.3
